socube/__init__.py
socube/__main__.py
socube/cube.py
socube/help.en_US.json
socube/help.zh_CN.json
socube/data/__init__.py
socube/data/loading.py
socube/data/preprocess.py
socube/data/visualize.py
socube/net/__init__.py
socube/net/_base.py
socube/net/_inception.py
socube/task/__init__.py
socube/task/doublet/__init__.py
socube/task/doublet/data.py
socube/task/doublet/model.py
socube/task/doublet/train.py
socube/train/__init__.py
socube/train/metrics.py
socube/train/strategy.py
socube/utils/__init__.py
socube/utils/concurrence.py
socube/utils/context.py
socube/utils/exception.py
socube/utils/io.py
socube/utils/logging.py
socube/utils/mail.py
socube/utils/memory.py
socube-1.1.dist-info/LICENSE
socube-1.1.dist-info/METADATA
socube-1.1.dist-info/WHEEL
socube-1.1.dist-info/entry_points.txt
socube-1.1.dist-info/top_level.txt
socube-1.1.dist-info/RECORD
