Metadata-Version: 2.1
Name: socube
Version: 1.1
Summary: A simple python package for doublet detection in scRNA-seq data
Home-page: https://github/GCS-ZHN/socube/
Author: Zhang.H.N
Author-email: zhang.h.n@foxmail.com
License: MIT License
Platform: any
Classifier: Environment :: Console
Classifier: Intended Audience :: Science/Research
Classifier: Topic :: Scientific/Engineering :: Bio-Informatics
Requires-Python: >=3.7
License-File: LICENSE
Requires-Dist: anndata (>=0.7.8)
Requires-Dist: matplotlib (>=3.5.0)
Requires-Dist: numpy (>=1.20.1)
Requires-Dist: pandas (>=1.3.4)
Requires-Dist: python-highcharts (>=0.4.2)
Requires-Dist: scanpy (>=1.8.2)
Requires-Dist: scikit-learn (>=1.0.1)
Requires-Dist: scipy (>=1.7.3)
Requires-Dist: tables (<=3.6.1)
Requires-Dist: lapjv (>=1.3.1)
Requires-Dist: torch (>=1.8.1)
Requires-Dist: torchvision (>=0.9.1)
Requires-Dist: tqdm (>=4.62.3)
Requires-Dist: umap-learn (>=0.5.2)
